markovanalyzer/__init__.py
markovanalyzer/fitting_tools.py
markovanalyzer/forward.py
markovanalyzer/gpu_backend.py
markovanalyzer/model_comparison_tools.py
markovanalyzer/njit_backend.py
markovanalyzer/polyspectra_calculator.py
markovanalyzer/wtd_fitting_tools.py
markovanalyzer-0.1.8.dist-info/METADATA
markovanalyzer-0.1.8.dist-info/WHEEL
markovanalyzer-0.1.8.dist-info/licenses/LICENSE
markovanalyzer-0.1.8.dist-info/RECORD
